[{"bundle_id":"com.bonnie39.cyleo","name":"Cydia","version":"1.0~b1","tagline":"A modern APT package manager.","homepage":"https://repo.bonnie39.com","developer":{"name":"Bonnie Anderson","email":"bwest671@icloud.com"},"maintainer":{"name":"Bonnie Anderson","email":"bwest671@icloud.com"},"social":[{"name":"Twitter","url":"https://twitter.com/dev_bonnie"},{"name":"Website","url":"https://bonnie39.com/"}],"section":"Packaging","pre_dependencies":"","dependencies":"","conflicts":"","replaces":"","provides":"","other_control":["Tag: role::enduser","SomeOtherEntryToControl: True"],"tint":"#a16f33","works_min":"12.0","works_max":"27.0","featured":"true","source":"https://github.com/Bonnie39/Cyleo","changelog":[{"version":"1.0~b1","changes":"Beta release."}]}]